CHANGES.txt
README.txt
ZPL.txt
setup.cfg
setup.py
haufe/__init__.py
haufe.releaser.egg-info/PKG-INFO
haufe.releaser.egg-info/SOURCES.txt
haufe.releaser.egg-info/dependency_links.txt
haufe.releaser.egg-info/entry_points.txt
haufe.releaser.egg-info/namespace_packages.txt
haufe.releaser.egg-info/not-zip-safe
haufe.releaser.egg-info/requires.txt
haufe.releaser.egg-info/top_level.txt
haufe/releaser/__init__.py
haufe/releaser/commands.py
haufe/releaser/rest.py
haufe/releaser/upload.py
