Metadata-Version: 1.0
Name: haufe.releaser
Version: 0.1.5
Summary: Performs local upload of distribution files to a haufe.eggserver instance
Home-page: UNKNOWN
Author: Andreas Jung
Author-email: andreas.jung@haufe.de
License: ZPL V2.1
Platform: UNKNOWN
Classifier: Programming Language :: Python
Classifier: Topic :: Software Development :: Libraries :: Python Modules
